ATARVA/__init__.py
ATARVA/baseline.py
ATARVA/cigar_utils.py
ATARVA/consensus.py
ATARVA/core.py
ATARVA/cstag_utils.py
ATARVA/darwin_libssw.so
ATARVA/decomp_utils.py
ATARVA/genotype_utils.py
ATARVA/libssw.so
ATARVA/locus_utils.py
ATARVA/md_utils.py
ATARVA/operation_utils.py
ATARVA/pyssw.py
ATARVA/realignment_utils.py
ATARVA/snp_utils.py
ATARVA/soft_clip_utils.py
ATARVA/somatic_utils.py
ATARVA/ssw_lib.py
ATARVA/sub_operation_utils.py
ATARVA/vcf_writer.py
ATARVA/version.py
atarva-0.5.0.dist-info/licenses/LICENSE
atarva-0.5.0.dist-info/METADATA
atarva-0.5.0.dist-info/WHEEL
atarva-0.5.0.dist-info/entry_points.txt
atarva-0.5.0.dist-info/top_level.txt
atarva-0.5.0.dist-info/RECORD
