Metadata-Version: 2.4
Name: ATaRVa
Version: 0.5.0
Summary: Analysis of Tandem Repeats Variations
Author-email: Divya Tej Sowpati <tej@ccmb.res.in>
Maintainer-email: Akshay Kumar Avvaru <avvaru@ccmb.res.in>, Abishek Kumar <abishekks@csirccmb.org>
License-Expression: MIT
Project-URL: Repository, https://github.com/sowpatilab/ATaRVa.git
Keywords: tandem repeats,repeats,long reads,ONT,PacBio,satellites,vntr,tr,microsatellites,macrosatellites,str
Classifier: Development Status :: 4 - Beta
Classifier: Programming Language :: Python :: 3.13
Classifier: Intended Audience :: Science/Research
Classifier: Topic :: Scientific/Engineering :: Bio-Informatics
Requires-Python: >=3.9
License-File: LICENSE
Requires-Dist: numpy>=1.26.4
Requires-Dist: pyabpoa>=1.5.3
Requires-Dist: pysam>=0.22.1
Requires-Dist: scikit-learn>=1.4.1
Requires-Dist: scipy>=1.12.0
Requires-Dist: threadpoolctl>=3.3.0
Requires-Dist: tqdm>=4.66.1
Requires-Dist: bitarray>=3.0.0
Requires-Dist: regex>=2025.9.1
Requires-Dist: hdbscan>=0.8.40
Dynamic: license-file
